rlauto/__init__.py
rlauto/cli.py
rlauto/multi_commit_chunker.py
rlauto/multi_commit_cleaner.py
rlauto/multi_commit_fetcher.py
rlauto/multi_commit_summarizer.py
rlauto/multi_post_release_notes_to_slack.py
rlauto/multi_post_user_notes_to_slack.py
rlauto/multi_release_formatter_llm.py
rlauto/multi_release_user_note_llm.py
release_note_automator-0.1.8.dist-info/METADATA
release_note_automator-0.1.8.dist-info/WHEEL
release_note_automator-0.1.8.dist-info/entry_points.txt
release_note_automator-0.1.8.dist-info/top_level.txt
release_note_automator-0.1.8.dist-info/RECORD
