Metadata-Version: 2.4
Name: release-note-automator
Version: 0.1.8
Summary: A CLI tool to automate fetching, cleaning, summarizing, and posting release notes from Azure DevOps.
Home-page: https://github.com/ankur-helak/release-note-automator
Author: Ankur Helak
Author-email: Ankur Helak <ankurhelak@gmail.com>
License: MIT
Project-URL: Homepage, https://github.com/ankur-helak/release-note-automator
Project-URL: Repository, https://github.com/ankur-helak/release-note-automator
Project-URL: Issues, https://github.com/ankur-helak/release-note-automator/issues
Keywords: release-notes,cli,azure-devops,automation
Classifier: Programming Language :: Python :: 3
Classifier: Operating System :: OS Independent
Classifier: License :: OSI Approved :: MIT License
Requires-Python: >=3.8
Requires-Dist: requests
Requires-Dist: python-dotenv
Requires-Dist: questionary
Requires-Dist: wcwidth
Dynamic: author
Dynamic: home-page
Dynamic: requires-python
